nonebot_plugin_xjie_weather/__init__.py
nonebot_plugin_xjie_weather/config.py
nonebot_plugin_xjie_weather/data_utilities.py
nonebot_plugin_xjie_weather/db/new_city.db
nonebot_plugin_xjie_weather/file_handle.py
nonebot_plugin_xjie_weather/get_weather.py
nonebot_plugin_xjie_weather/html_module.py
nonebot_plugin_xjie_weather/main.py
nonebot_plugin_xjie_weather/setup.py
nonebot_plugin_xjie_weather/src/css/fonts/AlimamaShuHeiTi-Bold.woff2
nonebot_plugin_xjie_weather/src/css/fonts/iconfont.woff2
nonebot_plugin_xjie_weather/src/css/fonts/qweather-icons.ttf
nonebot_plugin_xjie_weather/src/css/fonts/qweather-icons.woff
nonebot_plugin_xjie_weather/src/css/fonts/qweather-icons.woff2
nonebot_plugin_xjie_weather/src/css/qweather-icons.css
nonebot_plugin_xjie_weather/src/css/qweather-icons.json
nonebot_plugin_xjie_weather/src/css/style.css
nonebot_plugin_xjie_weather/src/image/dqy.svg
nonebot_plugin_xjie_weather/src/image/PM2.5-2-Outlined.svg
nonebot_plugin_xjie_weather/src/image/visibility.svg
nonebot_plugin_xjie_weather/src/index.html
nonebot_plugin_xjie_weather/src/output.html
nonebot_plugin_xjie_weather/weather_img_data.py
nonebot_plugin_xjie_weather/wx_info/amap.py
nonebot_plugin_xjie_weather/wx_info/qweather.py
nonebot_plugin_xjie_weather/wx_info/visualcrossing.py
nonebot_plugin_xjie_weather/wx_info/vvhan.py
nonebot_plugin_xjie_weather/xj_requests.py
nonebot_plugin_xjie_weather/xjie_data.json
nonebot_plugin_xjie_weather/xjie_db.py
nonebot_plugin_xjie_weather-1.2.4.dist-info/LICENSE
nonebot_plugin_xjie_weather-1.2.4.dist-info/METADATA
nonebot_plugin_xjie_weather-1.2.4.dist-info/WHEEL
nonebot_plugin_xjie_weather-1.2.4.dist-info/RECORD
