Metadata-Version: 2.1
Name: nonebot-plugin-xjie-weather
Version: 1.2.4
Summary: A little weather plugin
Home-page: https://github.com/ajdgg/nonebot-plugin-xjie-weather
License: LICENSE
Keywords: nonebot,nonebot2
Author: AwAjie
Author-email: 139576615+ajdgg@users.noreply.github.com
Requires-Python: >=3.9,<4.0
Classifier: License :: Other/Proprietary License
Classifier: Programming Language :: Python :: 3
Classifier: Programming Language :: Python :: 3.9
Classifier: Programming Language :: Python :: 3.10
Classifier: Programming Language :: Python :: 3.11
Classifier: Programming Language :: Python :: 3.12
Requires-Dist: Jinja2 (>=3.1.4,<4.0.0)
Requires-Dist: Pillow (>=10.4.0,<11.0.0)
Requires-Dist: httpx (>=0.27.0,<0.28.0)
Requires-Dist: nonebot-adapter-onebot (>=2.0.0-beta.1,<3.0.0)
Requires-Dist: nonebot-plugin-alconna (>=0.53.0,<0.54.0)
Requires-Dist: nonebot2 (>=2.2.0,<3.0.0)
Requires-Dist: playwright (>=1.44.0,<2.0.0)
Project-URL: Documentation, https://github.com/ajdgg/nonebot-plugin-xjie-weather
Project-URL: Repository, https://github.com/ajdgg/nonebot-plugin-xjie-weather
